{"github_data":{"https://github.com/batfish/batfish":{"contributors":{"count":75,"url":"https://github.com/batfish/batfish/graphs/contributors"},"description":"Batfish is a network configuration analysis tool that can find bugs and guarantee the correctness of (planned or current) network configurations. It enables network engineers to rapidly and safely evolve their network, without fear of outages or security breaches.","generated_at":"2024-08-27T02:43:03.015839631Z","latest_commit":{"ts":"2024-08-26T05:20:15Z","url":"https://github.com/batfish/batfish/commit/1d663a7872b9e6bc2953ca3b94e02121ef459669"},"participation_stats":[2,4,8,10,6,6,5,6,11,4,3,3,1,3,3,10,23,0,11,4,5,3,2,3,3,2,6,2,5,8,1,2,3,3,12,5,1,3,2,25,18,6,7,7,18,1,6,2,11,22,12,2],"stars":1139,"topics":["configuration","configuration-analysis","configuration-parser","network","network-analysis","network-automation","network-security","network-validation","network-verification"],"url":"https://github.com/batfish/batfish","first_commit":{"ts":"2014-05-29T19:15:33Z","url":"https://github.com/batfish/batfish/commit/88fe75ea2366cbf472adfac9d23684d447d23a13"},"languages":{"ANTLR":2007677,"HCL":49266,"Java":26661176,"Python":11181,"Shell":6603,"Starlark":240178},"latest_release":{"ts":"2024-07-10T18:01:23Z","url":"https://github.com/batfish/batfish/releases/tag/v2024.07.10"},"license":"Apache License 2.0"},"https://github.com/nautobot/nautobot":{"contributors":{"count":278,"url":"https://github.com/nautobot/nautobot/graphs/contributors"},"description":"Network Source of Truth & Network Automation Platform","generated_at":"2024-08-27T02:43:11.461185626Z","latest_commit":{"ts":"2024-08-26T19:57:10Z","url":"https://github.com/nautobot/nautobot/commit/38c1335dea51f5f7f2fba584965bc1537a4ddde4"},"participation_stats":[26,37,15,14,39,12,18,29,14,14,29,32,16,35,33,28,26,0,39,17,25,15,25,33,13,39,22,12,28,21,28,10,18,23,17,16,17,17,5,28,9,6,11,22,12,17,18,17,28,20,11,4],"stars":990,"topics":["dcim","hacktoberfest","ipam","nautobot","network-automation","python","sot"],"url":"https://github.com/nautobot/nautobot","first_commit":{"ts":"2016-03-01T16:23:03Z","url":"https://github.com/nautobot/nautobot/commit/27b289ee3b30ed3b0643a1c78c2e8caec329dcd2"},"languages":{"CSS":44196,"Dockerfile":11666,"Gherkin":14390,"HTML":1040255,"JavaScript":85013,"Jinja":29412,"Python":7588643,"Shell":9163},"latest_release":{"ts":"2024-08-19T19:52:51Z","url":"https://github.com/nautobot/nautobot/releases/tag/v2.3.1"},"license":"Apache License 2.0"},"https://github.com/netbox-community/netbox":{"contributors":{"count":370,"url":"https://github.com/netbox-community/netbox/graphs/contributors"},"description":"The premier source of truth powering network automation. Open source under Apache 2. Public demo: https://demo.netbox.dev","generated_at":"2024-08-27T02:43:12.947719457Z","latest_commit":{"ts":"2024-08-26T20:41:58Z","url":"https://github.com/netbox-community/netbox/commit/a7f83de8c4d3f17573556ecb72d537af7f6e8d17"},"participation_stats":[31,12,15,31,14,14,5,15,5,10,28,6,3,48,19,15,20,33,17,15,34,22,25,25,24,48,30,61,50,54,20,41,14,50,21,61,45,29,23,20,24,17,26,16,17,48,12,19,4,10,17,10],"stars":15650,"topics":["cabling","dcim","django","infrastructure-management","ipam","netbox","network","network-automation","python","sot","sysadmin"],"url":"https://github.com/netbox-community/netbox","first_commit":{"ts":"2016-03-01T16:23:03Z","url":"https://github.com/netbox-community/netbox/commit/27b289ee3b30ed3b0643a1c78c2e8caec329dcd2"},"languages":{"HTML":604507,"JavaScript":5296,"Jinja":2120,"Python":11742985,"SCSS":14709,"Shell":7604,"TypeScript":107598},"latest_release":{"ts":"2024-08-14T14:25:25Z","url":"https://github.com/netbox-community/netbox/releases/tag/v4.0.9"},"license":"Apache License 2.0"},"https://github.com/netenglabs/suzieq":{"contributors":{"count":29,"url":"https://github.com/netenglabs/suzieq/graphs/contributors"},"description":"Using network observability to operate and design healthier networks","generated_at":"2024-08-27T02:43:14.422288014Z","latest_commit":{"ts":"2024-06-03T01:20:06Z","url":"https://github.com/netenglabs/suzieq/commit/9362ae2296bf34fa9f82f7d3b7258134068b4f1e"},"participation_stats":[0,0,0,0,0,0,0,0,0,0,0,0,0,0,0,0,0,0,0,8,0,1,9,0,3,9,1,2,0,0,2,4,7,0,0,0,0,0,50,2,0,0,0,0,0,0,0,0,0,0,0,0],"stars":785,"topics":["data-center","datacenter","infrastructure","network-analysis","network-monitoring","network-validation","networking","python"],"url":"https://github.com/netenglabs/suzieq","first_commit":{"ts":"2020-01-07T14:11:10Z","url":"https://github.com/netenglabs/suzieq/commit/bae56ef39cf61902457791b7465389173f1106bb"},"languages":{"Dockerfile":1054,"Python":1642417,"Shell":8026},"latest_release":{"ts":"2024-01-10T15:20:17Z","url":"https://github.com/netenglabs/suzieq/releases/tag/v0.22.0"},"license":"Apache License 2.0"},"https://github.com/opsmill/infrahub":{"contributors":{"count":24,"url":"https://github.com/opsmill/infrahub/graphs/contributors"},"description":"Infrahub - A new approach to Infrastructure Management","generated_at":"2024-08-27T02:43:17.296991251Z","latest_commit":{"ts":"2024-08-26T15:39:37Z","url":"https://github.com/opsmill/infrahub/commit/033af52fb93c703b4c5e829dbb939ec6183d1d71"},"participation_stats":[107,149,147,134,49,50,50,90,89,114,104,132,114,113,32,136,91,64,163,166,109,157,167,196,128,121,234,245,232,148,66,130,128,138,122,126,70,180,220,79,97,53,32,30,75,67,37,33,36,45,72,30],"stars":178,"url":"https://github.com/opsmill/infrahub","first_commit":{"ts":"2022-08-25T10:29:45Z","url":"https://github.com/opsmill/infrahub/commit/66394fe8d209bf115dbf00cce50ffe52da192089"},"languages":{"CSS":8664,"Dockerfile":6359,"HTML":2523,"JavaScript":3963,"Jinja":10139,"MDX":11283,"Python":5627261,"Shell":2668,"Smarty":8521,"TypeScript":1693654},"latest_release":{"ts":"2024-08-13T13:57:09Z","url":"https://github.com/opsmill/infrahub/releases/tag/infrahub-v0.15.3"},"license":"GNU Affero General Public License v3.0"}},"items":[{"category":"Network state","homepage_url":"https://netboxlabs.com","id":"network-state--network-source-of-truth--netbox-community","logo":"logos/9ab3df7705c687c360e73964b97641d4a845d1ff8842fbbf1132291ba6c6610d.svg","name":"Netbox Community","subcategory":"Network Source of Truth","website":"https://netboxlabs.com","accepted_at":"2024-05-14","blog_url":"https://netboxlabs.com/blog/","crunchbase_url":"https://www.crunchbase.com/organization/netbox-labs","description":"NetBox is the leading solution for modeling and documenting modern networks.","docker_url":"https://hub.docker.com/r/netboxcommunity/netbox/","documentation_url":"https://netboxlabs.com/docs/netbox/en/stable/","featured":{"label":"Full Open Source","order":1},"maturity":"full-open-source","oss":true,"repositories":[{"url":"https://github.com/netbox-community/netbox","primary":true}],"summary":{"business_use_case":"Provides centralized network intended state and documentation as well as IPAM and DCIM and scripting functionality.","integration":"IP Fabric, Slurpit","intro_url":"https://youtu.be/jr9Pxx0NkTc","tags":["ipam","dcim","nsot","database"]},"tag":"nsot","twitter_url":"https://twitter.com/NetBoxOfficial","youtube_url":"https://www.youtube.com/channel/UCs5FgE5p03tP-8InKVIojdw"},{"category":"Network state","homepage_url":"https://www.opsmill.com","id":"network-state--network-source-of-truth--infrahub","logo":"logos/2ff0659a9c1349679cdd0ddce90b4eddd4638cef0471ffc5f4681ec2c394fb3d.svg","name":"InfraHub","subcategory":"Network Source of Truth","website":"https://www.opsmill.com","description":"Infrahub from OpsMill is taking a new approach to Infrastructure Management by providing a new generation of datastore to organize and control all the data that defines how an infrastructure should run. Infrahub offers a central hub to manage the data, templates and playbooks that powers your infrastructure by combining the version control and branch management capabilities of Git with the flexible data model and UI of a graph database.","featured":{"label":"Full Open Source","order":1},"maturity":"full-open-source","oss":true,"repositories":[{"url":"https://github.com/opsmill/infrahub","primary":true}]},{"category":"Network state","homepage_url":"https://nautobot.com/","id":"network-state--network-source-of-truth--nautobot","logo":"logos/ab8b3260edcb4a978e33ce8aa4b9539ea5ba3a47101c4911b83b931e0ffc63c6.png","name":"Nautobot","subcategory":"Network Source of Truth","website":"https://nautobot.com/","description":"Nautobot is a Network Source of Truth and Network Automation Platform.","featured":{"label":"Full Open Source","order":1},"maturity":"full-open-source","oss":true,"repositories":[{"url":"https://github.com/nautobot/nautobot","primary":true}]},{"category":"Network state","homepage_url":"https://ipfabric.io","id":"network-state--network-discovery--ip-fabric","logo":"logos/caa0fcef8f855e67a7420ff12bee3c586c73828e1dbdb60ada1e2abe19f7c79d.svg","name":"IP Fabric","subcategory":"Network Discovery","website":"https://ipfabric.io","crunchbase_url":"https://www.crunchbase.com/organization/ip-fabric","description":"IP Fabric is a network infrastructure visibility and analytics solution helping enterprise network&security teams deliver network assurance and automation.","featured":{"label":"Enterprise (Custom Pricing)","order":6},"maturity":"enterprise","summary":{"business_use_case":"Visibility for brownfield network assurance by discovering and modeling the network infrastructure by collecting data from the devices using credentials and APIs.","integration":"Netbox","tags":["network assurance","network visibility","network analytics","network discovery","network modeling"],"use_case":"Discovery and modeling and assurance of network infrastructure with multivendor support allowing you to view the high level network design and drill down to the device or technology level."},"twitter_url":"https://x.com/IPFabric"},{"category":"Network state","homepage_url":"https://slurpit.io","id":"network-state--network-discovery--slurpit","logo":"logos/c4212051c1389337cede5c3b385416c620f4d7dfdde086fb3e37fc1d3808b5e2.png","name":"Slurpit","subcategory":"Network Discovery","website":"https://slurpit.io","crunchbase_url":"https://www.crunchbase.com/organization/cloud-native-computing-foundation","description":"Slurp’it is a powerful and easy-to-use network discovery solution that offers 100% accurate network inventory. No coding required.","featured":{"label":"Freemium (Limited Free Version)","order":3},"maturity":"freemium","summary":{"business_use_case":"[10 free licence shenanigans] Provides a network inventory and discovery solution that is easy to use and accurate.","integration":"Netbox","use_case":"discovery and inventory with a focus on ease of use and accuracy. No coding required."}},{"category":"Network state","homepage_url":"https://www.suzieq.io/","id":"network-state--testing-compliance---querying--suzieq","logo":"logos/93ca0a0e3c703bb44c6404c21a613eeef875bbda55987bd0d3ee12f2509cf6d7.png","name":"SuzieQ","subcategory":"Testing, Compliance & Querying","website":"https://www.suzieq.io/","description":"An open-source, multivendor network observability platform for cloud-first networks.","featured":{"label":"Full Open Source","order":1},"maturity":"full-open-source","oss":true,"repositories":[{"url":"https://github.com/netenglabs/suzieq","primary":true}]},{"category":"Network state","homepage_url":"https://netpicker.io","id":"network-state--testing-compliance---querying--netpicker","logo":"logos/87bc632804d57ffdc69a33bef959f60dbb54026e4d20637a3a2932ed61c09c98.png","name":"Netpicker","subcategory":"Testing, Compliance & Querying","website":"https://netpicker.io","description":"Test the design, security and compliance of your network, A Python-based testing platform for your network","featured":{"label":"Freemium (Limited Free Version)","order":3},"maturity":"freemium","summary":{"integration":"Netbox, Slurpit","tags":["network testing","device_backup","change-validation","compliance","configuration security"],"use_case":"[free 10 device Shenanigans licence] Network configuration testing, Configuration backups and compliance with a hardening config and security angle. Needs 3rd party discovery tool or manual add devices"},"twitter_url":"https://x.com/IPFabric"},{"category":"Network state","homepage_url":"https://www.batfish.org/","id":"network-state--testing-compliance---querying--batfish","logo":"logos/432bd5e7034140a460c597bf8c7b50976eca8a8778ca80c54c91d68b606af43e.png","name":"Batfish","subcategory":"Testing, Compliance & Querying","website":"https://www.batfish.org/","description":"A network configuration analysis tool that builds a mathematical model of network behavior, allowing for advanced querying and validation.","featured":{"label":"Hybrid (Open Core with Proprietary Extensions)","order":8},"maturity":"hybrid","oss":true,"repositories":[{"url":"https://github.com/batfish/batfish","primary":true}]}]}