{"projects":{"accepted_at":{"2024-05":1},"accepted_at_rt":{"2024-05":1},"category":{"Automation Tooling":{"projects":17,"subcategories":{"Automation Platforms and Management":12,"Continuous Configuration Automation (CCA)":3,"Network Programmability Frameworks":2}},"Network state":{"projects":14,"subcategories":{"Network Discovery/Assurance":4,"Network Source of Truth":3,"Testing, Compliance & Querying":7}},"Telemetry and observability":{"projects":13,"subcategories":{"Monitoring & Alerting":10,"Observability":1,"Telemetry & Data Collection":2}},"Virtualization":{"projects":5,"subcategories":{"Network virtualization platforms":5}}},"maturity":{"commercial-only":1,"enterprise":9,"free-restrictive":1,"freemium":4,"full-open-source":24,"hybrid":6,"saas":4},"projects":49,"tag":{"nsot":1}},"repositories":{"bytes":384134366,"contributors":22469,"languages":{"CSS":9,"Go":10,"HTML":12,"JavaScript":12,"Jinja":11,"MDX":4,"Python":20,"Roff":4,"SCSS":7,"TypeScript":6},"languages_bytes":{"C":18796106,"C++":3238820,"Go":136180046,"Groovy":13054726,"HTML":2225336,"Java":31433993,"JavaScript":4053781,"PHP":37619094,"Python":92123866,"TypeScript":30766579},"licenses":{"Apache License 2.0":13,"BSD 3-Clause \"New\" or \"Revised\" License":1,"GNU Affero General Public License v3.0":3,"GNU General Public License v2.0":1,"GNU General Public License v3.0":2,"MIT License":2,"Mozilla Public License 2.0":1,"Other":4},"participation_stats":[777,957,963,1021,921,847,915,961,864,946,916,1002,734,776,844,896,422,398,819,890,945,972,1028,958,869,1034,1053,1062,1083,1048,625,877,922,856,975,764,912,765,821,684,880,504,512,472,482,516,484,471,501,513,510,454],"repositories":29,"stars":313294}}